__init__.py
lawquery/__init__.py
lawquery/engine.py
lawquery/documents/bo-luat-dan-su-2015.json.gz
lawquery/documents/bo-luat-hang-hai-viet-nam-2015.json.gz
lawquery/documents/bo-luat-hinh-su-2015.json.gz
lawquery/documents/bo-luat-lao-dong-2019.json.gz
lawquery/documents/bo-luat-to-tung-dan-su-2015.json.gz
lawquery/documents/bo-luat-to-tung-hinh-su-2015.json.gz
lawquery-0.0.2.dist-info/LICENSE
lawquery-0.0.2.dist-info/METADATA
lawquery-0.0.2.dist-info/WHEEL
lawquery-0.0.2.dist-info/top_level.txt
lawquery-0.0.2.dist-info/RECORD
