Metadata-Version: 2.1
Name: lawquery
Version: 0.0.2
Summary: Query Vietnamese law documents
Home-page: https://github.com/Th1nhNg0/law-query
Author: Th1nhNg0
Author-email: thinhngow@gmail.com
License: MIT
Classifier: License :: OSI Approved :: MIT License
Classifier: Programming Language :: Python :: 3.9
Classifier: Operating System :: OS Independent
License-File: LICENSE
